{
    "prepare_queue": {
        "installed": [],
        "uninstalled": []
    },
    "config_munge": {
        "files": {}
    },
    "installed_plugins": {
        "cordova-plugin-app-event": {
            "PACKAGE_NAME": "com.slowrollbuffalo.app"
        },
        "cordova-plugin-console": {
            "PACKAGE_NAME": "com.slowrollbuffalo.app"
        },
        "cordova-plugin-device": {
            "PACKAGE_NAME": "com.slowrollbuffalo.app"
        },
        "cordova-plugin-whitelist": {
            "PACKAGE_NAME": "com.slowrollbuffalo.app"
        },
        "de.appplant.cordova.plugin.local-notification": {
            "PACKAGE_NAME": "com.slowrollbuffalo.app"
        },
        "cordova-plugin-geolocation": {
            "PACKAGE_NAME": "com.slowrollbuffalo.app"
        },
        "cordova-plugin-dialogs": {
            "PACKAGE_NAME": "com.slowrollbuffalo.app"
        },
        "com.telerik.plugins.nativepagetransitions": {
            "PACKAGE_NAME": "org.slowrollbuffalo.app"
        }
    },
    "dependent_plugins": {}
}